eagleowl/__init__.py
eagleowl/__main__.py
eagleowl/client.py
eagleowl/executor.py
eagleowl/loggers.py
eagleowl/manifest.py
eagleowl-0.0.10.dist-info/METADATA
eagleowl-0.0.10.dist-info/WHEEL
eagleowl-0.0.10.dist-info/entry_points.txt
eagleowl-0.0.10.dist-info/top_level.txt
eagleowl-0.0.10.dist-info/RECORD
