Metadata-Version: 2.1
Name: eagleowl
Version: 0.0.10
Summary: A tool for installing sophisticated Kubernetes application consisting of numerous components and intricate configurations.
Author-email: Rui Xiao <rui.xiao@hcl-software.com>
Project-URL: Homepage, https://www.actian.com/databases/vector/
Requires-Python: >=3.6
Requires-Dist: PyYAML
